MANIFEST.in
setup.py
ajax_select/LICENSE.txt
ajax_select/__init__.py
ajax_select/admin.py
ajax_select/fields.py
ajax_select/models.py
ajax_select/urls.py
ajax_select/views.py
ajax_select/static/css/ajax_select.css
ajax_select/static/images/loading-indicator.gif
ajax_select/static/js/ajax_select.js
ajax_select/templates/autocomplete.html
ajax_select/templates/autocompleteselect.html
ajax_select/templates/autocompleteselectmultiple.html
bob_ajax_selects.egg-info/PKG-INFO
bob_ajax_selects.egg-info/SOURCES.txt
bob_ajax_selects.egg-info/dependency_links.txt
bob_ajax_selects.egg-info/pbr.json
bob_ajax_selects.egg-info/top_level.txt
example/README.txt
example/__init__.py
example/admin.py
example/forms.py
example/install.sh
example/lookups.py
example/manage.py
example/models.py
example/settings.py
example/urls.py
example/views.py