Metadata-Version: 1.1
Name: bob-ajax-selects
Version: 1.6
Summary: jQuery-powered auto-complete fields for editing ForeignKey, ManyToManyField and CharField
Home-page: https://github.com/quamilek/bob-ajax-selects/
Author: Kamil Warguła, crucialfelix
Author-email: kwargula@gmail.com crucialfelix@gmail.com
License: UNKNOWN
Platform: UNKNOWN
Classifier: Programming Language :: Python
Classifier: Programming Language :: Python :: 2
Classifier: Development Status :: 5 - Production/Stable
Classifier: Environment :: Web Environment
Classifier: Intended Audience :: Developers
Classifier: License :: OSI Approved :: MIT License
Classifier: Operating System :: OS Independent
Classifier: Topic :: Software Development :: Libraries :: Python Modules
Classifier: Topic :: Software Development :: User Interfaces
Classifier: Framework :: Django
